lndb_rest_instance/__init__.py
lndb_rest_instance/main.py
lndb_rest_instance/routers/__init__.py
lndb_rest_instance/routers/introspection.py
lndb_rest_instance/routers/metadata.py
lndb_rest_instance-0.2.0.dist-info/WHEEL
lndb_rest_instance-0.2.0.dist-info/METADATA
lndb_rest_instance-0.2.0.dist-info/RECORD
