Metadata-Version: 2.1
Name: lndb_rest_instance
Version: 0.2.0
Summary: Rest API for a specific instance.
Author-email: Lamin Labs <laminlabs@gmail.com>
Requires-Dist: nbproject
Requires-Dist: fastapi[uvicorn]
Requires-Dist: uvicorn[standard]
Requires-Dist: lamindb==0.17.0
Requires-Dist: pre-commit ; extra == "dev"
Requires-Dist: nox ; extra == "dev"
Requires-Dist: pytest>=6.0 ; extra == "test"
Requires-Dist: pytest-cov ; extra == "test"
Project-URL: Home, https://github.com/laminlabs/lndb-rest-instance
Provides-Extra: dev
Provides-Extra: test
